odoo10_addon_quality_control_team-10.0.1.0.0.99.dev7-py2.7-nspkg.pth
odoo/addons/quality_control_team/README.rst
odoo/addons/quality_control_team/__init__.py
odoo/addons/quality_control_team/__manifest__.py
odoo/addons/quality_control_team/data/quality_control_team_data.xml
odoo/addons/quality_control_team/i18n/de.po
odoo/addons/quality_control_team/i18n/pt.po
odoo/addons/quality_control_team/i18n/quality_control_team.pot
odoo/addons/quality_control_team/models/__init__.py
odoo/addons/quality_control_team/models/qc_team.py
odoo/addons/quality_control_team/models/res_partner.py
odoo/addons/quality_control_team/models/res_user.py
odoo/addons/quality_control_team/security/ir.model.access.csv
odoo/addons/quality_control_team/static/description/icon.png
odoo/addons/quality_control_team/static/description/icon.svg
odoo/addons/quality_control_team/tests/__init__.py
odoo/addons/quality_control_team/tests/test_quality_control_team.py
odoo/addons/quality_control_team/views/qc_team_dashboard.xml
odoo/addons/quality_control_team/views/qc_team_view.xml
odoo10_addon_quality_control_team-10.0.1.0.0.99.dev7.dist-info/METADATA
odoo10_addon_quality_control_team-10.0.1.0.0.99.dev7.dist-info/RECORD
odoo10_addon_quality_control_team-10.0.1.0.0.99.dev7.dist-info/WHEEL
odoo10_addon_quality_control_team-10.0.1.0.0.99.dev7.dist-info/namespace_packages.txt
odoo10_addon_quality_control_team-10.0.1.0.0.99.dev7.dist-info/top_level.txt
